litexrpl/Eng.py
litexrpl/Misc.py
litexrpl/Wallet.py
litexrpl/__init__.py
litexrpl-1.1.0.dist-info/LICENSE
litexrpl-1.1.0.dist-info/METADATA
litexrpl-1.1.0.dist-info/WHEEL
litexrpl-1.1.0.dist-info/top_level.txt
litexrpl-1.1.0.dist-info/RECORD
